summary.rst
baseconfig/__init__.py
baseconfig/configuration.py
baseconfig/exceptions.py
baseconfig/py.typed
baseconfig/validators.py
baseconfig-1.1.0.dist-info/METADATA
baseconfig-1.1.0.dist-info/WHEEL
baseconfig-1.1.0.dist-info/top_level.txt
baseconfig-1.1.0.dist-info/RECORD
