Metadata-Version: 2.4
Name: baseconfig
Version: 1.1.0
Summary: The configuration package which handles multiple sources, fallback from one source to another, and internal validation of the values.
Home-page: http://go.pelicandd.com/n/baseconfig
Author: Arseni Mourzenko
Author-email: arseni.mourzenko@pelicandd.com
License: MIT
Keywords: flask
Dynamic: author
Dynamic: author-email
Dynamic: description
Dynamic: home-page
Dynamic: keywords
Dynamic: license
Dynamic: summary
